pyrws/__init__.py
pyrws/__main__.py
pyrws/checks.py
pyrws/cli.py
pyrws/constants.py
pyrws/core.py
pyrws/plotting.py
pyrws/utils.py
pyrws/version.py
pyrws-0.4.1.dist-info/METADATA
pyrws-0.4.1.dist-info/WHEEL
pyrws-0.4.1.dist-info/licenses/LICENSE
pyrws-0.4.1.dist-info/RECORD
